README.md
setup.py
ansible/module_utils/selvpc_utils/__init__.py
ansible/module_utils/selvpc_utils/common.py
ansible/module_utils/selvpc_utils/floatingips.py
ansible/module_utils/selvpc_utils/licenses.py
ansible/module_utils/selvpc_utils/limits.py
ansible/module_utils/selvpc_utils/projects.py
ansible/module_utils/selvpc_utils/quotas.py
ansible/module_utils/selvpc_utils/roles.py
ansible/module_utils/selvpc_utils/subnets.py
ansible/module_utils/selvpc_utils/users.py
ansible/module_utils/selvpc_utils/wrappers.py
ansible/modules/selvpc/__init__.py
ansible/modules/selvpc/selvpc_capabilities.py
ansible/modules/selvpc/selvpc_floatingips.py
ansible/modules/selvpc/selvpc_licenses.py
ansible/modules/selvpc/selvpc_limits.py
ansible/modules/selvpc/selvpc_projects.py
ansible/modules/selvpc/selvpc_quotas.py
ansible/modules/selvpc/selvpc_roles.py
ansible/modules/selvpc/selvpc_subnets.py
ansible/modules/selvpc/selvpc_tokens.py
ansible/modules/selvpc/selvpc_users.py
ansible_selvpc_modules.egg-info/PKG-INFO
ansible_selvpc_modules.egg-info/SOURCES.txt
ansible_selvpc_modules.egg-info/dependency_links.txt
ansible_selvpc_modules.egg-info/requires.txt
ansible_selvpc_modules.egg-info/top_level.txt