Metadata-Version: 1.0
Name: ansible-selvpc-modules
Version: 1.1
Summary: Ansible modules for Selectel VPC platform
Home-page: UNKNOWN
Author: Rutskiy Daniil
Author-email: rutskiy@selectel.ru
License: UNKNOWN
Platform: UNKNOWN
